combigeo.cpython-313-darwin.so
your_module_name.cpython-313-darwin.so
combigeo-0.0.1.dist-info/METADATA
combigeo-0.0.1.dist-info/WHEEL
combigeo-0.0.1.dist-info/top_level.txt
combigeo-0.0.1.dist-info/RECORD
