Metadata-Version: 2.1
Name: combigeo
Version: 0.0.1
Summary: Python wrapper for C++ Run function
